fakepkg/__init__.py
fakepkg-0.1.0.dist-info/entry_points.txt
fakepkg-0.1.0.dist-info/WHEEL
fakepkg-0.1.0.dist-info/METADATA
fakepkg-0.1.0.dist-info/RECORD
